{
  "users": [
    {
      "id": 1,
      "name": "Jason"
    },
    {
      "id": 2,
      "name": "Michel"
    },
    {
      "id": 3,
      "name": "Dora"
    },
    {
      "id": 4,
      "name": "Justin"
    }
  ],
  "projects": [
    {
      "id": 1,
      "name": "Delivery Management",
      "personId": 1,
      "organization": "Delivery Group",
      "created": 1604989757139
    },
    {
      "id": 2,
      "name": "Business To Team APP",
      "personId": 2,
      "organization": "B2T Group",
      "created": 1604989757139
    },
    {
      "id": 3,
      "name": "MaterialManagementSystem",
      "personId": 2,
      "organization": "material group",
      "created": 1546300800000
    },
    {
      "id": 4,
      "name": "HeadquartersManagementSystem",
      "personId": 3,
      "organization": "Headquarters",
      "created": 1604980000011
    },
    {
      "id": 5,
      "name": "food delivery route planning system",
      "personId": 4,
      "organization": "Delivery Group",
      "created": 1546900800000
    }
  ]
}